xander_ai/__init__.py
xander_ai/xander.py
xander_ai/AIUnified/Chatbot.py
xander_ai/AIUnified/ChatbotPDF.py
xander_ai/AIUnified/ClassificationDL.py
xander_ai/AIUnified/ClassificationML.py
xander_ai/AIUnified/Forecaster.py
xander_ai/AIUnified/ImageModelTrainer.py
xander_ai/AIUnified/ImageTrainer.py
xander_ai/AIUnified/RegressionDL.py
xander_ai/AIUnified/RegressionML.py
xander_ai/AIUnified/RegressionUnified.py
xander_ai/AIUnified/TextModel.py
xander_ai/AIUnified/TextUnified.py
xander_ai/AIUnified/__init__.py
xander_ai/AIUnified/chatbot_interference.py
xander_ai/__pycache__/__init__.cpython-312.pyc
xander_ai/__pycache__/xander.cpython-312.pyc
xander_ai-0.2.7.dist-info/METADATA
xander_ai-0.2.7.dist-info/WHEEL
xander_ai-0.2.7.dist-info/top_level.txt
xander_ai-0.2.7.dist-info/RECORD
