Metadata-Version: 2.1
Name: xander-ai
Version: 0.2.7
Summary: Xander - A package to train Classification, Regression, and Image Classification models.
Author: Atulit Gaur
Author-email: atulit23@gmail.com
Classifier: Programming Language :: Python :: 3
Classifier: License :: OSI Approved :: MIT License
Classifier: Operating System :: OS Independent
Requires-Dist: pandas
Requires-Dist: numpy
Requires-Dist: chardet
Requires-Dist: tensorflow
Requires-Dist: scikit-learn
Requires-Dist: openpyxl
Requires-Dist: channels
Requires-Dist: asgiref
Requires-Dist: keras
Requires-Dist: keras-tuner
Requires-Dist: joblib
Requires-Dist: requests
Requires-Dist: nltk
Requires-Dist: matplotlib
Requires-Dist: xgboost
